aitl_test_pkg-1.0.dist-info/DESCRIPTION.rst
aitl_test_pkg-1.0.dist-info/METADATA
aitl_test_pkg-1.0.dist-info/RECORD
aitl_test_pkg-1.0.dist-info/WHEEL
aitl_test_pkg-1.0.dist-info/metadata.json
aitl_test_pkg-1.0.dist-info/top_level.txt
test/__init__.py
test/operation.py
